[
  {
    "vessel-name": "Islander",
    "stats": {
      "unitSystem": "Standard"
    },
    "engines": {},
    "generators": {},
    "electricMotors": {},
    "shafts": {},
    "props": {},
    "thrusters": {},
    "rudders": {},
    "grates": {},
    "zincs": {},
    "doors": {},
    "misc": {}
  },
  {
    "vessel-name": "Delta Billy",
    "stats": {
      "unitSystem": "standard"
    },
    "engines": {},
    "generators": {},
    "electricMotors": {},
    "shafts": {},
    "props": {},
    "thrusters": {},
    "rudders": {},
    "grates": {},
    "zincs": {
      "zincs-Entry-1": {
        "location-1": "hull",
        "count-1": "28",
        "material-1": "aluminum",
        "location-2": "propeller",
        "count-2": "38",
        "material-2": "aluminum",
        "location-3": "rope-guard",
        "count-3": "12",
        "material-3": "aluminum",
        "location-4": "sea-chest",
        "count-4": "6",
        "material-4": "aluminum",
        "location-5": "rudder",
        "count-5": "6",
        "material-5": "aluminum"
      }
    },
    "doors": {},
    "misc": {}
  },
  {
    "vessel-name": "Tioga",
    "stats": {
      "unitSystem": "standard"
    },
    "engines": {},
    "generators": {},
    "electricMotors": {},
    "shafts": {},
    "props": {},
    "thrusters": {},
    "rudders": {},
    "grates": {},
    "zincs": {
      "zincs-Entry-1": {
        "location-1": "hull",
        "count-1": "20",
        "material-1": "zinc",
        "location-2": "rope-guard",
        "count-2": "4",
        "material-2": "zinc",
        "location-3": "propeller",
        "count-3": "15",
        "material-3": "zinc",
        "location-4": "sea-chest",
        "count-4": "1",
        "material-4": "zinc"
      }
    },
    "doors": {},
    "misc": {}
  },
  {
    "vessel-name": "Del Norte",
    "stats": {
      "unitSystem": "standard"
    },
    "engines": {},
    "generators": {},
    "electricMotors": {},
    "shafts": {},
    "props": {},
    "thrusters": {},
    "rudders": {},
    "grates": {},
    "zincs": {},
    "doors": {},
    "misc": {}
  },
  {
    "vessel-name": "Azteca",
    "stats": {
      "unitSystem": "standard"
    },
    "engines": {},
    "generators": {},
    "electricMotors": {},
    "shafts": {},
    "props": {},
    "thrusters": {},
    "rudders": {},
    "grates": {},
    "zincs": {},
    "doors": {},
    "misc": {}
  },
  {
    "vessel-name": "test",
    "stats": {
      "unitSystem": "standard"
    },
    "engines": {},
    "generators": {},
    "electricMotors": {},
    "shafts": {},
    "props": {},
    "thrusters": {},
    "rudders": {},
    "grates": {},
    "zincs": {
      "zincs-Entry-1": {
        "location-1": "hull",
        "material-1": "zinc"
      }
    },
    "doors": {},
    "misc": {}
  },
  {
    "vessel-name": "Intrepid",
    "stats": {
      "unitSystem": "standard"
    },
    "engines": {},
    "generators": {},
    "electricMotors": {},
    "shafts": {},
    "props": {},
    "thrusters": {},
    "rudders": {},
    "grates": {},
    "zincs": {},
    "doors": {},
    "misc": {}
  },
  {
    "vessel-name": "Rsc-3",
    "stats": {
      "unitSystem": "standard"
    },
    "engines": {},
    "generators": {},
    "electricMotors": {},
    "shafts": {},
    "props": {},
    "thrusters": {},
    "rudders": {},
    "grates": {},
    "zincs": {},
    "doors": {},
    "misc": {}
  }
]